<annotation><folder>VOC</folder><filename>20220816_100GOPRO_G0060730.JPG</filename><size><width>5568</width><height>4176</height><depth>3</depth></size><object><name>non_o2</name><pose>Unspecified</pose><truncated>0</truncated><difficult>0</difficult><bndbox><xmin>3681</xmin><ymin>11</ymin><xmax>5559</xmax><ymax>1603</ymax></bndbox></object><object><name>non_o2</name><pose>Unspecified</pose><truncated>0</truncated><difficult>0</difficult><bndbox><xmin>3338</xmin><ymin>1406</ymin><xmax>5553</xmax><ymax>3004</ymax></bndbox></object><object><name>o2</name><pose>Unspecified</pose><truncated>0</truncated><difficult>0</difficult><bndbox><xmin>2451</xmin><ymin>2284</ymin><xmax>5553</xmax><ymax>3643</ymax></bndbox></object><object><name>o2</name><pose>Unspecified</pose><truncated>0</truncated><difficult>0</difficult><bndbox><xmin>1121</xmin><ymin>952</ymin><xmax>2445</xmax><ymax>3815</ymax></bndbox></object><object><name>non_o2</name><pose>Unspecified</pose><truncated>0</truncated><difficult>0</difficult><bndbox><xmin>1606</xmin><ymin>3034</ymin><xmax>2788</xmax><ymax>4172</ymax></bndbox></object><object><name>non_o2</name><pose>Unspecified</pose><truncated>0</truncated><difficult>0</difficult><bndbox><xmin>3948</xmin><ymin>3773</ymin><xmax>5559</xmax><ymax>4169</ymax></bndbox></object></annotation>