<annotation><folder>VOC</folder><filename>20220816_100GOPRO_G0060884.JPG</filename><size><width>5568</width><height>4176</height><depth>3</depth></size><object><name>o2</name><pose>Unspecified</pose><truncated>0</truncated><difficult>0</difficult><bndbox><xmin>2016</xmin><ymin>1981</ymin><xmax>3009</xmax><ymax>4169</ymax></bndbox></object><object><name>non_o2</name><pose>Unspecified</pose><truncated>0</truncated><difficult>0</difficult><bndbox><xmin>0</xmin><ymin>3705</ymin><xmax>710</xmax><ymax>4169</ymax></bndbox></object><object><name>non_o2</name><pose>Unspecified</pose><truncated>0</truncated><difficult>0</difficult><bndbox><xmin>115</xmin><ymin>3250</ymin><xmax>819</xmax><ymax>3962</ymax></bndbox></object><object><name>non_o2</name><pose>Unspecified</pose><truncated>0</truncated><difficult>0</difficult><bndbox><xmin>943</xmin><ymin>2067</ymin><xmax>2097</xmax><ymax>4169</ymax></bndbox></object><object><name>non_o2</name><pose>Unspecified</pose><truncated>0</truncated><difficult>0</difficult><bndbox><xmin>4279</xmin><ymin>1864</ymin><xmax>5559</xmax><ymax>3073</ymax></bndbox></object><object><name>non_o2</name><pose>Unspecified</pose><truncated>0</truncated><difficult>0</difficult><bndbox><xmin>2607</xmin><ymin>1585</ymin><xmax>5071</xmax><ymax>2909</ymax></bndbox></object><object><name>non_o2</name><pose>Unspecified</pose><truncated>0</truncated><difficult>0</difficult><bndbox><xmin>4317</xmin><ymin>11</ymin><xmax>5184</xmax><ymax>662</ymax></bndbox></object><object><name>o2</name><pose>Unspecified</pose><truncated>0</truncated><difficult>0</difficult><bndbox><xmin>2865</xmin><ymin>0</ymin><xmax>4356</xmax><ymax>1425</ymax></bndbox></object><object><name>o2</name><pose>Unspecified</pose><truncated>0</truncated><difficult>0</difficult><bndbox><xmin>1372</xmin><ymin>253</ymin><xmax>4072</xmax><ymax>1687</ymax></bndbox></object><object><name>non_o2</name><pose>Unspecified</pose><truncated>0</truncated><difficult>0</difficult><bndbox><xmin>228</xmin><ymin>8</ymin><xmax>1103</xmax><ymax>603</ymax></bndbox></object><object><name>non_o2</name><pose>Unspecified</pose><truncated>0</truncated><difficult>0</difficult><bndbox><xmin>0</xmin><ymin>627</ymin><xmax>1269</xmax><ymax>1918</ymax></bndbox></object><object><name>non_o2</name><pose>Unspecified</pose><truncated>0</truncated><difficult>0</difficult><bndbox><xmin>4329</xmin><ymin>2975</ymin><xmax>5556</xmax><ymax>4169</ymax></bndbox></object><object><name>non_o2</name><pose>Unspecified</pose><truncated>0</truncated><difficult>0</difficult><bndbox><xmin>2777</xmin><ymin>3877</ymin><xmax>4713</xmax><ymax>4172</ymax></bndbox></object><object><name>non_o2</name><pose>Unspecified</pose><truncated>0</truncated><difficult>0</difficult><bndbox><xmin>2499</xmin><ymin>2746</ymin><xmax>4987</xmax><ymax>4139</ymax></bndbox></object><object><name>non_o2</name><pose>Unspecified</pose><truncated>0</truncated><difficult>0</difficult><bndbox><xmin>5057</xmin><ymin>1201</ymin><xmax>5562</xmax><ymax>1987</ymax></bndbox></object><object><name>non_o2</name><pose>Unspecified</pose><truncated>0</truncated><difficult>0</difficult><bndbox><xmin>1819</xmin><ymin>3</ymin><xmax>2281</xmax><ymax>201</ymax></bndbox></object><object><name>non_o2</name><pose>Unspecified</pose><truncated>0</truncated><difficult>0</difficult><bndbox><xmin>825</xmin><ymin>930</ymin><xmax>3086</xmax><ymax>2423</ymax></bndbox></object></annotation>